dotcat/__init__.py
dotcat/__main__.py
dotcat/__version__.py
dotcat/cli.py
dotcat/completers.py
dotcat/core.py
dotcat/data_access.py
dotcat/dotcat.py
dotcat/formatting.py
dotcat/help_text.py
dotcat/output_formatters.py
dotcat/parsers.py
zsh/README.md
zsh/__init__.py
zsh/_dotcat
zsh/direct-test.py
zsh/dotcat-completion.py
zsh/install_completions.py
zsh/test-argcomplete.sh
zsh/test-completion.zsh
zsh/test-global-argcomplete.sh
zsh/test-modified-completion.py
zsh/test-pipx-completion.sh
dotcat-0.9.6.dist-info/LICENSE
dotcat-0.9.6.dist-info/METADATA
dotcat-0.9.6.dist-info/WHEEL
dotcat-0.9.6.dist-info/entry_points.txt
dotcat-0.9.6.dist-info/RECORD
